tobii_research-2.1.0.data/purelib/tobii_research.py
tobii_research-2.1.0.data/purelib/tobiiresearch/__init__.py
tobii_research-2.1.0.data/purelib/tobiiresearch/implementation/Calibration.py
tobii_research-2.1.0.data/purelib/tobiiresearch/implementation/DisplayArea.py
tobii_research-2.1.0.data/purelib/tobiiresearch/implementation/Errors.py
tobii_research-2.1.0.data/purelib/tobiiresearch/implementation/ExternalSignalData.py
tobii_research-2.1.0.data/purelib/tobiiresearch/implementation/EyeImageData.py
tobii_research-2.1.0.data/purelib/tobiiresearch/implementation/EyeOpennessData.py
tobii_research-2.1.0.data/purelib/tobiiresearch/implementation/EyeTracker.py
tobii_research-2.1.0.data/purelib/tobiiresearch/implementation/GazeData.py
tobii_research-2.1.0.data/purelib/tobiiresearch/implementation/License.py
tobii_research-2.1.0.data/purelib/tobiiresearch/implementation/Notifications.py
tobii_research-2.1.0.data/purelib/tobiiresearch/implementation/ScreenBasedCalibration.py
tobii_research-2.1.0.data/purelib/tobiiresearch/implementation/ScreenBasedMonocularCalibration.py
tobii_research-2.1.0.data/purelib/tobiiresearch/implementation/StreamErrorData.py
tobii_research-2.1.0.data/purelib/tobiiresearch/implementation/TimeSynchronizationData.py
tobii_research-2.1.0.data/purelib/tobiiresearch/implementation/UserPositionGuide.py
tobii_research-2.1.0.data/purelib/tobiiresearch/implementation/_LogEntry.py
tobii_research-2.1.0.data/purelib/tobiiresearch/implementation/__init__.py
tobii_research-2.1.0.data/purelib/tobiiresearch/internal/Enum.py
tobii_research-2.1.0.data/purelib/tobiiresearch/internal/__init__.py
tobii_research-2.1.0.data/purelib/tobiiresearch/interop/__init__.py
tobii_research-2.1.0.data/purelib/tobiiresearch/interop/interop.py
tobii_research-2.1.0.data/purelib/tobiiresearch/interop/python2/__init__.py
tobii_research-2.1.0.data/purelib/tobiiresearch/interop/python3/__init__.py
tobii_research-2.1.0.data/purelib/tobiiresearch/interop/python3/tobii_research_interop.pyd
tobii_research-2.1.0.dist-info/METADATA
tobii_research-2.1.0.dist-info/WHEEL
tobii_research-2.1.0.dist-info/top_level.txt
tobii_research-2.1.0.dist-info/RECORD
