Metadata-Version: 2.1
Name: tobii-research
Version: 2.1.0
Summary: The Tobii Pro SDK is a tool for letting you interact easily with your eye tracker and write your own
Home-page: http://developer.tobiipro.com/
Author: Tobii AB
Author-email: tobiiprosdk@tobii.com
License: https://go.tobii.com/tobii-pro-sdk-license-agreement
Keywords: tobii research eyetracking sdk tobiipro
Platform: UNKNOWN
Classifier: Development Status :: 5 - Production/Stable
Classifier: Intended Audience :: Developers
Classifier: Topic :: Software Development :: Build Tools
Classifier: License :: Other/Proprietary License
Classifier: Programming Language :: Python :: 3.10
Provides-Extra: dev
Requires-Dist: check-manifest; extra == "dev"
Provides-Extra: test
Requires-Dist: coverage; extra == "test"
